pointslicer/__init__.py
pointslicer/pointslicer.cpython-39-arm-linux-gnueabihf.so
pointslicer-0.1.0.dist-info/METADATA
pointslicer-0.1.0.dist-info/WHEEL
pointslicer-0.1.0.dist-info/RECORD
