Metadata-Version: 2.4
Name: pointslicer
Version: 0.1.0
Classifier: Programming Language :: Rust
Classifier: Programming Language :: Python :: Implementation :: CPython
Classifier: Programming Language :: Python :: Implementation :: PyPy
Classifier: License :: OSI Approved :: GNU General Public License v3 (GPLv3)
Classifier: Operating System :: OS Independent
Classifier: Topic :: Scientific/Engineering :: GIS
Classifier: Topic :: Scientific/Engineering :: Visualization
Classifier: Topic :: System :: Filesystems
Summary: Python bindings for pointslicer - extract points from LAS/LAZ files using GeoPackage tile indices
License-Expression: GPL-3.0
Requires-Python: >=3.8
Project-URL: Documentation, https://docs.rs/pointslicer-core
Project-URL: Homepage, https://github.com/stefan-kuepper/pointslicer
Project-URL: Repository, https://github.com/stefan-kuepper/pointslicer
